{"password":"5678","deleted":[{"read":"x","subject":"This is subject 3","from":"21312@gmail.com","to":["12312@gmail.com"],"time":"2021-02-20T08:30:00","content":"This is content for s3.","tags":["CS2113"]},{"read":"x","subject":"This is subject 4","from":"21312@gmail.com","to":["12312@gmail.com"],"time":"2021-02-20T09:30:00","content":"This is content for s4.","tags":["School"]},{"read":"x","subject":"This is subject 8","from":"12312@gmail.com","to":["11111@gmail.com"],"time":"2021-02-20T13:30:00","content":"This is content for s8.","tags":["IMPT"]},{"read":"x","subject":"This is subject 11","from":"21312@gmail.com","to":["12312@gmail.com","12313@gmail.com","12314@gmail.com"],"time":"2021-02-20T16:30:00","content":"This is content for s1. ","tags":[]},{"read":"x","subject":"This is subject 1","from":"21312@gmail.com","to":["12312@gmail.com"],"time":"2021-02-20T06:30:00","content":"This is content for s1.","tags":[]}],"junk":[],"drafts":[{"read":"x","subject":"This is subject 3","from":"12312@gmail.com","to":["test@yahoo.com"],"time":"2021-02-20T08:30:00","content":"This is content for s3.","tags":[]},{"read":"x","subject":"LilySubject","from":"12312@gmail.com","to":["lily@gmail.com"],"time":"2021-03-30T15:30:09","content":"hehe\nhehe\nhaha\n","tags":[]}],"archive":[{"read":"x","subject":"This is subject 5","from":"21312@gmail.com","to":["12312@gmail.com"],"time":"2021-02-20T10:30:00","content":"This is content for s5.","tags":[]},{"read":"x","subject":"This is subject 6","from":"11312@gmail.com","to":["12312@gmail.com"],"time":"2021-02-20T11:30:00","content":"This is content for s6.","tags":[]},{"read":"x","subject":"This is subject 4","from":"21312@gmail.com","to":["12312@gmail.com"],"time":"2021-02-20T09:30:00","content":"This is content for s4.","tags":[]}],"inbox":[{"read":"x","subject":"S1","from":"testC@gmail.com","to":["12312@gmail.com"],"time":"2021-04-09T13:08:33","content":"C1","tags":[]},{"read":"x","subject":"S2","from":"testA@gmail.com","to":["12312@gmail.com"],"time":"2021-04-09T13:08:33","content":"C2","tags":[]},{"read":"x","subject":"S1","from":"testC@gmail.com","to":["12312@gmail.com"],"time":"2021-04-09T13:08:33","content":"C1","tags":[]}],"sent":[{"read":"x","subject":"This is subject 7","from":"12312@gmail.com","to":["12332@gmail.com"],"time":"2021-02-20T12:30:00","content":"This is content for s7.","tags":["CS2113","IMPT"]}],"account":"12312@gmail.com"}